{
	"credit": "Made with Blockbench",
	"textures": {
		"0": "block/copper_block",
		"2": "block/coal_block",
		"8": "block/anvil",
		"particle": "block/copper_block"
	},
	"elements": [
		{
			"from": [3, 3, 3],
			"to": [13, 4, 13],
			"faces": {
				"north": {"uv": [0, 0, 10, 1], "texture": "#8"},
				"east": {"uv": [0, 0, 10, 1], "texture": "#8"},
				"south": {"uv": [0, 0, 10, 1], "texture": "#8"},
				"west": {"uv": [0, 0, 10, 1], "texture": "#8"},
				"up": {"uv": [0, 0, 10, 10], "texture": "#8"},
				"down": {"uv": [0, 0, 10, 10], "texture": "#8"}
			}
		},
		{
			"from": [4, 4, 4],
			"to": [12, 5, 12],
			"faces": {
				"north": {"uv": [0, 0, 8, 1], "texture": "#8"},
				"east": {"uv": [0, 0, 8, 1], "texture": "#8"},
				"south": {"uv": [0, 0, 8, 1], "texture": "#8"},
				"west": {"uv": [0, 0, 8, 1], "texture": "#8"},
				"up": {"uv": [0, 0, 8, 8], "texture": "#8"},
				"down": {"uv": [0, 0, 8, 8], "texture": "#8"}
			}
		},
		{
			"from": [5, 5, 5],
			"to": [11, 6, 11],
			"faces": {
				"north": {"uv": [0, 0, 6, 1], "texture": "#8"},
				"east": {"uv": [0, 0, 6, 1], "texture": "#8"},
				"south": {"uv": [0, 0, 6, 1], "texture": "#8"},
				"west": {"uv": [0, 0, 6, 1], "texture": "#8"},
				"up": {"uv": [0, 0, 6, 6], "texture": "#8"},
				"down": {"uv": [0, 0, 6, 6], "texture": "#8"}
			}
		},
		{
			"from": [2, 2, 2],
			"to": [14, 3, 14],
			"faces": {
				"north": {"uv": [0, 0, 12, 1], "texture": "#8"},
				"east": {"uv": [0, 0, 12, 1], "texture": "#8"},
				"south": {"uv": [0, 0, 12, 1], "texture": "#8"},
				"west": {"uv": [0, 0, 12, 1], "texture": "#8"},
				"up": {"uv": [0, 0, 12, 12], "texture": "#8"},
				"down": {"uv": [0, 0, 12, 12], "texture": "#8"}
			}
		},
		{
			"from": [1, 1, 1],
			"to": [15, 2, 15],
			"faces": {
				"north": {"uv": [0, 0, 14, 1], "texture": "#8"},
				"east": {"uv": [0, 0, 14, 1], "texture": "#8"},
				"south": {"uv": [0, 0, 14, 1], "texture": "#8"},
				"west": {"uv": [0, 0, 14, 1], "texture": "#8"},
				"up": {"uv": [0, 0, 14, 14], "texture": "#8"},
				"down": {"uv": [0, 0, 14, 14], "texture": "#8"}
			}
		},
		{
			"from": [0, 0, 0],
			"to": [16, 1, 16],
			"faces": {
				"north": {"uv": [0, 0, 16, 1], "texture": "#8"},
				"east": {"uv": [0, 0, 16, 1], "texture": "#8"},
				"south": {"uv": [0, 0, 16, 1], "texture": "#8"},
				"west": {"uv": [0, 0, 16, 1], "texture": "#8"},
				"up": {"uv": [0, 0, 16, 16], "texture": "#8"},
				"down": {"uv": [0, 0, 16, 16], "texture": "#8", "cullface": "down"}
			}
		},
		{
			"from": [4, 13, 4],
			"to": [12, 14, 12],
			"faces": {
				"north": {"uv": [0, 0, 8, 1], "texture": "#0"},
				"east": {"uv": [0, 0, 8, 1], "texture": "#0"},
				"south": {"uv": [0, 0, 8, 1], "texture": "#0"},
				"west": {"uv": [0, 0, 8, 1], "texture": "#0"},
				"up": {"uv": [0, 0, 8, 8], "texture": "#0"},
				"down": {"uv": [0, 0, 8, 8], "texture": "#0"}
			}
		},
		{
			"from": [5, 14, 5],
			"to": [11, 15, 11],
			"faces": {
				"north": {"uv": [0, 0, 6, 1], "texture": "#0"},
				"east": {"uv": [0, 0, 6, 1], "texture": "#0"},
				"south": {"uv": [0, 0, 6, 1], "texture": "#0"},
				"west": {"uv": [0, 0, 6, 1], "texture": "#0"},
				"up": {"uv": [0, 0, 6, 6], "texture": "#0"}
			}
		},
		{
			"from": [5, 12, 5],
			"to": [11, 12.5, 11],
			"faces": {
				"north": {"uv": [0, 0, 6, 0.5], "texture": "#0"},
				"east": {"uv": [0, 0, 6, 0.5], "texture": "#0"},
				"south": {"uv": [0, 0, 6, 0.5], "texture": "#0"},
				"west": {"uv": [0, 0, 6, 0.5], "texture": "#0"},
				"up": {"uv": [0, 0, 6, 6], "texture": "#0"},
				"down": {"uv": [0, 0, 6, 6], "texture": "#0"}
			}
		},
		{
			"from": [5, 11, 5],
			"to": [11, 11.5, 11],
			"faces": {
				"north": {"uv": [0, 0, 6, 0.5], "texture": "#0"},
				"east": {"uv": [0, 0, 6, 0.5], "texture": "#0"},
				"south": {"uv": [0, 0, 6, 0.5], "texture": "#0"},
				"west": {"uv": [0, 0, 6, 0.5], "texture": "#0"},
				"up": {"uv": [0, 0, 6, 6], "texture": "#0"},
				"down": {"uv": [0, 0, 6, 6], "texture": "#0"}
			}
		},
		{
			"from": [7, 15, 7],
			"to": [9, 16, 9],
			"faces": {
				"north": {"uv": [0, 0, 2, 1], "texture": "#0"},
				"east": {"uv": [0, 0, 2, 1], "texture": "#0"},
				"south": {"uv": [0, 0, 2, 1], "texture": "#0"},
				"west": {"uv": [0, 0, 2, 1], "texture": "#0"},
				"up": {"uv": [0, 0, 2, 2], "texture": "#0"}
			}
		},
		{
			"from": [6, 4, 6],
			"to": [10, 13, 10],
			"faces": {
				"north": {"uv": [5, 1, 9, 6], "texture": "#2"},
				"east": {"uv": [5, 1, 9, 6], "texture": "#2"},
				"south": {"uv": [5, 1, 9, 6], "texture": "#2"},
				"west": {"uv": [5, 1, 9, 6], "texture": "#2"}
			}
		}
	],
	"groups": [
		{
			"name": "group",
			"origin": [0, 0, 0],
			"color": 0,
			"children": [0, 1, 2, 3, 4, 5, 6, 7, 8, 9, 10, 11]
		}
	]
}